AsyncWebsocketStreamInterface/AsyncWebsocketStreamInterface.py
AsyncWebsocketStreamInterface/__init__.py
AsyncWebsocketStreamInterface-1.0.5.dist-info/LICENSE
AsyncWebsocketStreamInterface-1.0.5.dist-info/METADATA
AsyncWebsocketStreamInterface-1.0.5.dist-info/WHEEL
AsyncWebsocketStreamInterface-1.0.5.dist-info/top_level.txt
AsyncWebsocketStreamInterface-1.0.5.dist-info/RECORD
