Metadata-Version: 2.1
Name: AsyncWebsocketStreamInterface
Version: 1.0.5
Summary: Exchange one normal asynchronous websocket connection to unlimited number of data streams.
Home-page: https://github.com/monk-after-90s/AsyncWebsocketStreamInterface
Author: Antas
License: MIT
Platform: UNKNOWN
Classifier: Programming Language :: Python :: 3
Classifier: License :: OSI Approved :: MIT License
Classifier: Operating System :: OS Independent
Requires-Python: >=3.7
License-File: LICENSE
Requires-Dist: beeprint
Requires-Dist: websockets
Requires-Dist: ensureTaskCanceled
Requires-Dist: loguru
Requires-Dist: NoLossAsyncGenerator
Requires-Dist: AsyncExclusivePeriods
